{
  "title": "Bystander Game",
  "description": "",
  "initial_scene": "Scene 1",
  "version": "2.4.6",
  "last_edit": "2023-08-14 10:53:16",
  "published": "false",
  "scene_order": [
    "0",
    "1",
    "2",
    "3"
  ],
  "variables": [
    {
      "name": "var0",
      "value": "0",
      "value_type": "Float",
      "id": "22551"
    },
    {
      "name": "Age",
      "value": "",
      "value_type": "String",
      "id": "22550"
    }
  ],
  "proj_status": [],
  "research_variables": [
    {
      "name": "Gender",
      "id": "22548",
      "value_type": "String",
      "research_type": "Independent",
      "level_type": "Categorical",
      "domain": [
        "Male",
        "Female"
      ]
    },
    {
      "name": "Playingwithfriendsoralone",
      "id": "22553",
      "value_type": "String",
      "research_type": "Independent",
      "level_type": "Categorical",
      "domain": [
        "Introvert",
        "Extrovert"
      ]
    },
    {
      "name": "IntrovertorExtrovert",
      "id": "22553",
      "value_type": "String",
      "research_type": "Independent",
      "level_type": "Categorical",
      "domain": [
        "Introvert",
        "Extrovert"
      ]
    }
  ],
  "hypotheses": [
    "Men? or women? Are more likely to intervene during a domestic disput if they are alone? or with friends?"
  ]
}