{
  "dictNodes": {
    "0": {
      "name": "Start",
      "next": "52",
      "tru": "True",
      "index": "0",
      "posX": "-8.447178",
      "posY": "1.133318",
      "minimized": "False",
      "advance_mode": "OnClick",
      "type": "start"
    },
    "48": {
      "content": "You are at a new hip ice cream shop celebrating your friends daughters  birthday.",
      "owner": null,
      "speaking": "True",
      "name": "Dialogue",
      "next": "112",
      "tru": "True",
      "index": "48",
      "posX": "-2.143329",
      "posY": "0.7988008",
      "minimized": "False",
      "advance_mode": "OnClick",
      "type": "dialogue"
    },
    "49": {
      "content": "But then...",
      "owner": null,
      "speaking": "True",
      "name": "Dialogue",
      "next": "53",
      "tru": "True",
      "index": "49",
      "posX": "5.344903",
      "posY": "0.9218506",
      "minimized": "False",
      "advance_mode": "OnClick",
      "type": "dialogue"
    },
    "52": {
      "action": "play_background",
      "clipName": "Radios",
      "volume": "1",
      "name": "Sound",
      "next": "48",
      "tru": "True",
      "index": "52",
      "posX": "-5.529858",
      "posY": "0.5890378",
      "minimized": "False",
      "advance_mode": "OnClick",
      "type": "sound"
    },
    "53": {
      "action": "stop_loop1",
      "clipName": "",
      "volume": "1",
      "name": "Sound",
      "next": "54",
      "tru": "True",
      "index": "53",
      "posX": "8.517925",
      "posY": "1.633866",
      "minimized": "False",
      "advance_mode": "OnClick",
      "type": "sound"
    },
    "54": {
      "action": "play_background",
      "clipName": "Tense",
      "volume": "1",
      "name": "Sound",
      "next": "57",
      "tru": "True",
      "index": "54",
      "posX": "11.46375",
      "posY": "0.5479953",
      "minimized": "False",
      "advance_mode": "OnClick",
      "type": "sound"
    },
    "57": {
      "content": "\"MOM! I want a freakin milkshake!!\"",
      "owner": null,
      "speaking": "True",
      "name": "Dialogue",
      "next": "68",
      "tru": "True",
      "index": "57",
      "posX": "15.15565",
      "posY": "1.015614",
      "minimized": "False",
      "advance_mode": "OnClick",
      "type": "dialogue"
    },
    "58": {
      "action": "play_sound",
      "clipName": "Gun",
      "volume": "1",
      "name": "Sound",
      "next": "61",
      "tru": "True",
      "index": "58",
      "posX": "25.10925",
      "posY": "2.974277",
      "minimized": "False",
      "advance_mode": "OnClick",
      "type": "sound"
    },
    "61": {
      "action": "stop_background",
      "clipName": "",
      "volume": "1",
      "name": "Sound",
      "next": "65",
      "tru": "True",
      "index": "61",
      "posX": "28.11384",
      "posY": "4.06806",
      "minimized": "False",
      "advance_mode": "OnClick",
      "type": "sound"
    },
    "65": {
      "content": "The son had slapped the mom!\nShe was obviously injured with a bloody nose and in shock",
      "owner": null,
      "speaking": "True",
      "name": "Dialogue",
      "next": "67",
      "tru": "True",
      "index": "65",
      "posX": "31.02618",
      "posY": "3.369617",
      "minimized": "False",
      "advance_mode": "OnClick",
      "type": "dialogue"
    },
    "67": {
      "nextScript": "Scene 3 copy 3",
      "transitionText": "What would you do...?",
      "variablePairs": "",
      "name": "end",
      "next": "-1",
      "tru": "True",
      "index": "67",
      "posX": "35.15091",
      "posY": "3.67271",
      "minimized": "False",
      "advance_mode": "OnClick",
      "type": "end"
    },
    "68": {
      "content": "\"No son, not today.\"",
      "owner": null,
      "speaking": "True",
      "name": "Dialogue",
      "next": "69",
      "tru": "True",
      "index": "68",
      "posX": "19.08725",
      "posY": "2.552395",
      "minimized": "False",
      "advance_mode": "OnClick",
      "type": "dialogue"
    },
    "69": {
      "content": "\"If you don't give me a milkshake I WILL HURT YOU!\"",
      "owner": null,
      "speaking": "True",
      "name": "Dialogue",
      "next": "58",
      "tru": "True",
      "index": "69",
      "posX": "22.24552",
      "posY": "2.790526",
      "minimized": "False",
      "advance_mode": "OnClick",
      "type": "dialogue"
    },
    "112": {
      "content": "All of your friends were there having a great time.",
      "owner": null,
      "speaking": "True",
      "name": "Dialogue",
      "next": "49",
      "tru": "True",
      "index": "112",
      "posX": "1.732192",
      "posY": "0.9241362",
      "minimized": "False",
      "advance_mode": "OnClick",
      "type": "dialogue"
    }
  },
  "scene": {
    "name": "Scene 1",
    "title": "Scene 2 copy 2",
    "pos": {
      "x": 0.0,
      "y": 0.0,
      "z": 0.0
    },
    "uid": "13215",
    "background": "park_ice_cream_1",
    "furniture": [
      {
        "uid": 0,
        "rotation": 0.0,
        "visible": true,
        "locked": true,
        "color": "FFFFFF",
        "textcolor": "000000",
        "image": "park_ice_cream_1",
        "value": 0.0,
        "text": "",
        "fontSize": 0,
        "parentName": "",
        "objectType": 3,
        "thisOC": null,
        "name": "Background",
        "pos": {
          "x": 0.0,
          "y": 0.0,
          "z": 0.0
        },
        "size": {
          "x": 960.0,
          "y": 540.0
        }
      },
      {
        "uid": 1,
        "rotation": 0.0,
        "visible": true,
        "locked": false,
        "color": "FFFFFF",
        "textcolor": "000000",
        "image": "borna_child_asian_1",
        "value": 0.0,
        "text": "",
        "fontSize": 0,
        "parentName": "",
        "objectType": 4,
        "thisOC": null,
        "name": "borna_child_asian_1",
        "pos": {
          "x": -428.2166,
          "y": -202.259811,
          "z": 0.0
        },
        "size": {
          "x": 134.369171,
          "y": 134.369171
        }
      },
      {
        "uid": 2,
        "rotation": 0.0,
        "visible": true,
        "locked": false,
        "color": "FFFFFF",
        "textcolor": "000000",
        "image": "borna_daughter_1",
        "value": 0.0,
        "text": "",
        "fontSize": 0,
        "parentName": "",
        "objectType": 4,
        "thisOC": null,
        "name": "borna_daughter_1",
        "pos": {
          "x": -276.87912,
          "y": -155.12088,
          "z": 0.0
        },
        "size": {
          "x": 233.426514,
          "y": 233.426514
        }
      },
      {
        "uid": 3,
        "rotation": 358.755859,
        "visible": true,
        "locked": false,
        "color": "FFFFFF",
        "textcolor": "000000",
        "image": "female_10",
        "value": 0.0,
        "text": "",
        "fontSize": 0,
        "parentName": "",
        "objectType": 4,
        "thisOC": null,
        "name": "female_10",
        "pos": {
          "x": -6.828537,
          "y": -113.286987,
          "z": 0.0
        },
        "size": {
          "x": 68.00812,
          "y": 258.058228
        }
      },
      {
        "uid": 4,
        "rotation": 0.0,
        "visible": true,
        "locked": false,
        "color": "FFFFFF",
        "textcolor": "000000",
        "image": "female_construction_1",
        "value": 0.0,
        "text": "",
        "fontSize": 0,
        "parentName": "",
        "objectType": 4,
        "thisOC": null,
        "name": "female_construction_1",
        "pos": {
          "x": 435.241425,
          "y": -119.611687,
          "z": 0.0
        },
        "size": {
          "x": -80.0,
          "y": 289.0
        }
      },
      {
        "uid": 5,
        "rotation": 0.0,
        "visible": true,
        "locked": false,
        "color": "FFFFFF",
        "textcolor": "000000",
        "image": "male_14",
        "value": 0.0,
        "text": "",
        "fontSize": 0,
        "parentName": "",
        "objectType": 4,
        "thisOC": null,
        "name": "male_14",
        "pos": {
          "x": 101.453232,
          "y": -147.6283,
          "z": 0.0
        },
        "size": {
          "x": -63.4631462,
          "y": 240.631088
        }
      },
      {
        "uid": 6,
        "rotation": 0.0,
        "visible": true,
        "locked": false,
        "color": "FFFFFF",
        "textcolor": "000000",
        "image": "male_sitting_8",
        "value": 0.0,
        "text": "",
        "fontSize": 0,
        "parentName": "",
        "objectType": 4,
        "thisOC": null,
        "name": "male_sitting_8",
        "pos": {
          "x": 212.934982,
          "y": -80.56999,
          "z": 0.0
        },
        "size": {
          "x": 128.0,
          "y": 275.0
        }
      },
      {
        "uid": 7,
        "rotation": 330.53418,
        "visible": true,
        "locked": false,
        "color": "FFFFFF",
        "textcolor": "000000",
        "image": "baby_1",
        "value": 0.0,
        "text": "",
        "fontSize": 0,
        "parentName": "",
        "objectType": 4,
        "thisOC": null,
        "name": "baby_1",
        "pos": {
          "x": 222.535156,
          "y": -102.959747,
          "z": 0.0
        },
        "size": {
          "x": 53.1734924,
          "y": 81.9757843
        }
      },
      {
        "uid": 8,
        "rotation": 0.0,
        "visible": true,
        "locked": false,
        "color": "FFFFFF",
        "textcolor": "000000",
        "image": "female_construction_4",
        "value": 0.0,
        "text": "",
        "fontSize": 0,
        "parentName": "",
        "objectType": 4,
        "thisOC": null,
        "name": "female_construction_4",
        "pos": {
          "x": 351.5085,
          "y": -120.780075,
          "z": 0.0
        },
        "size": {
          "x": 80.0,
          "y": 289.0
        }
      },
      {
        "uid": 9,
        "rotation": 0.0,
        "visible": true,
        "locked": false,
        "color": "FFFFFF",
        "textcolor": "000000",
        "image": "steward_1Sprite",
        "value": 0.0,
        "text": "",
        "fontSize": 0,
        "parentName": "",
        "objectType": 4,
        "thisOC": null,
        "name": "steward_1",
        "pos": {
          "x": -105.075813,
          "y": -109.064339,
          "z": 0.0
        },
        "size": {
          "x": 63.5885162,
          "y": 266.508667
        }
      }
    ],
    "recent_assets": [],
    "recent_backgrounds": [],
    "recent_characters": [],
    "layoutScale": 0.7493424,
    "layoutPosition": {
      "x": 68.55552,
      "y": 8.499047
    },
    "scriptorScale": 1.0,
    "scriptorPosition": {
      "x": -153.962662,
      "y": -140.569473
    },
    "layoutParamSet": true,
    "scriptorParamSet": true
  },
  "started": false
}